{"name":{"2300":"La Botana","9208":"The Shire Cafe","9738":"Brew Coffee and Tea","5304":"Green Corner Restaurant","332":"El Caprichoso Hot Dogs Estilo Sonora","8757":"Red Leg Burgers & Bratwurst","9198":"Pita Palace","2219":"Pok\u00c3\u00a9 Eats","6320":"El New Yorican Central Catering & Delivery","4706":"Lakeside Hideout Cafe"},"address":{"2300":"4344 W Indian School Rd, Ste 34","9208":"1000 E Apache Blvd","9738":"2935 N Dysart Rd, Ste 7","5304":"1038 W Southern Ave, Ste 1","332":"2826 N 35th Ave","8757":"270 E Hunt Hwy, Ste 20","9198":"1445 W Southern Ave","2219":"2960 S Alma School Rd, Ste 3","6320":"8433 W Peoria Ave","4706":"11225 N 28th Dr, Ste A110"},"city":{"2300":"Phoenix","9208":"Tempe","9738":"Avondale","5304":"Mesa","332":"Phoenix","8757":"San Tan Valley","9198":"Mesa","2219":"Chandler","6320":"Peoria","4706":"Phoenix"},"state":{"2300":"AZ","9208":"AZ","9738":"AZ","5304":"AZ","332":"AZ","8757":"AZ","9198":"AZ","2219":"AZ","6320":"AZ","4706":"AZ"},"postal_code":{"2300":85031,"9208":85281,"9738":85392,"5304":85210,"332":85009,"8757":85143,"9198":85202,"2219":85286,"6320":85345,"4706":85029},"latitude":{"2300":33.49570763,"9208":33.41518,"9738":33.4800981,"5304":33.3944636,"332":33.479886,"8757":33.16307765,"9198":33.3892,"2219":33.26242277,"6320":33.58109374,"4706":33.58877944},"longitude":{"2300":-112.1538351,"9208":-111.924076,"9738":-112.3389945,"5304":-111.8541437,"332":-112.134721,"8757":-111.5627595,"9198":-111.86058,"2219":-111.859867,"6320":-112.2404557,"4706":-112.1198586},"stars":{"2300":5.0,"9208":5.0,"9738":5.0,"5304":5.0,"332":5.0,"8757":5.0,"9198":5.0,"2219":5.0,"6320":5.0,"4706":5.0},"review_count":{"2300":3,"9208":3,"9738":3,"5304":355,"332":14,"8757":4,"9198":3,"2219":25,"6320":94,"4706":26},"categories":{"2300":"mexican;seafood;restaurants;tacos","9208":"coffee & tea;bakeries;cafes;food;restaurants","9738":"restaurants;food;coffee & tea;breakfast & brunch","5304":"restaurants;salad;mediterranean;sandwiches;halal;arabian","332":"restaurants;hot dogs;street vendors;fast food;food","8757":"restaurants;chicken wings;burgers","9198":"restaurants;greek","2219":"japanese;restaurants;food;poke;hawaiian","6320":"caribbean;restaurants;spanish;puerto rican","4706":"coffee & tea;pizza;sandwiches;restaurants;breakfast & brunch;food"},"category":{"2300":"Mexican","9208":"American","9738":"American","5304":"Mediterranean","332":"American","8757":"American","9198":"Mediterranean","2219":"Japanese","6320":"Caribbean","4706":"Italian"}}